{
  "updated_at": "2026-05-06T04:12:42+00:00",
  "lookback_hours": 48,
  "model": "Mistral Large",
  "status": "ok",
  "hotspots": [
    {
      "id": "manuel-adornis-illicit-enrichment-scandal",
      "title": "Manuel Adorni’s illicit enrichment scandal",
      "blurb": "Argentina’s Chief of Cabinet Manuel Adorni faces intense scrutiny over allegations of illicit enrichment, including $245,000 in cash payments for home renovations without proper documentation. The scandal has sparked judicial investigations and public outrage, with calls for his resignation.",
      "affect": "This scandal commands disproportionate attention due to its moral outrage framing, cross-source repetition, and the perceived hypocrisy of a government official accused of corruption amid austerity measures.",
      "intensity": 5,
      "affect_signals": [
        "moral outrage framing",
        "cross-source repetition",
        "leadership crisis tone",
        "alarmist framing",
        "polarized contention"
      ],
      "categories": [
        "La Libertad Avanza"
      ],
      "article_count": 150,
      "refs": [
        {
          "title": "La Justicia avanza sobre el celular del contratista vinculado a Manuel Adorni",
          "source": "diariolapluma.com.ar",
          "url": "https://diariolapluma.com.ar/la-justicia-avanza-sobre-el-celular-del-contratista-vinculado-a-manuel-adorni/",
          "date": "2026-05-06T02:28:17+00:00",
          "category": "argentina"
        },
        {
          "title": "Ordenan peritar el celular del arquitecto que contrató Manuel Adorni para las lujosas obras de su casa",
          "source": "MinutoUno",
          "url": "https://www.minutouno.com/politica/ordenan-peritar-el-celular-del-arquitecto-que-contrato-manuel-adorni-las-lujosas-obras-su-casa-n6274370",
          "date": "2026-05-06T02:22:12+00:00",
          "category": "argentina"
        },
        {
          "title": "Se conoció un video de las refacciones en la casa de Adorni en Indio Cúa que habrían costado 245.000 dólares",
          "source": "Perfil",
          "url": "https://www.perfil.com/noticias/politica/se-conocieron-videos-de-las-refacciones-en-la-casa-de-adorni-en-indio-cua-que-habrian-costado-245000-dolares.phtml",
          "date": "2026-05-06T02:09:00+00:00",
          "category": "argentina"
        },
        {
          "title": "El capricho Adorni: cómo el gobierno Milei se está pegando un tiro en el pie por no echar a su vocero",
          "source": "TN",
          "url": "https://tn.com.ar/opinion/2026/05/05/el-capricho-adorni-como-el-gobierno-milei-se-esta-pegando-un-tiro-en-el-pie-por-no-echar-a-su-vocero/",
          "date": "2026-05-05T23:50:20+00:00",
          "category": "argentina"
        },
        {
          "title": "Desde que asumió como funcionario, Manuel Adorni gastó 752.480 dólares",
          "source": "todojujuy.com",
          "url": "https://www.todojujuy.com/desde-que-asumio-como-funcionario-manuel-adorni-gasto-752480-dolares-n289731",
          "date": "2026-05-05T22:58:00+00:00",
          "category": "argentina"
        },
        {
          "title": "Manuel Adorni le dijo que podía contar con él. Revisarán el celular del contratista para buscar mensajes borrados",
          "source": "La Nación",
          "url": "https://www.lanacion.com.ar/politica/manuel-adorni-le-dijo-que-podia-contar-con-el-revisaran-el-celular-del-contratista-para-buscar-nid05052026/",
          "date": "2026-05-05T21:59:00+00:00",
          "category": "argentina"
        },
        {
          "title": "Milei sigue respaldando a Manuel Adorni, a pesar de que se siguen sumando nuevos elementos sobre su presunto enriquecimiento ilícito",
          "source": "ladiaria.com.uy",
          "url": "https://ladiaria.com.uy/mundo/articulo/2026/5/milei-sigue-respaldando-a-manuel-adorni-a-pesar-de-que-se-siguen-sumando-nuevos-elementos-sobre-su-presunto-enriquecimiento-ilicito/",
          "date": "2026-05-05T21:35:58+00:00",
          "category": "argentina"
        },
        {
          "title": "El fiscal Pollicita rechazó el pedido de detención contra Manuel Adorni",
          "source": "Crónica",
          "url": "https://www.cronica.com.ar/politica/el-fiscal-pollicita-rechazo-el-pedido-de-detencion-contra-manuel-adorni-3135/",
          "date": "2026-05-05T20:40:32+00:00",
          "category": "argentina"
        },
        {
          "title": "La Justicia ordena peritar el teléfono del contratista de Manuel Adorni",
          "source": "Crónica",
          "url": "https://www.cronica.com.ar/politica/la-justicia-ordena-peritar-el-telefono-del-contratista-de-manuel-adorni-8242/",
          "date": "2026-05-05T19:44:48+00:00",
          "category": "argentina"
        },
        {
          "title": "Manuel Adorni no se va: Milei sostiene al vocero, pese al escándalo y las advertencias de parte del Gabinete",
          "source": "Letra P",
          "url": "https://www.letrap.com.ar/politica/manuel-adorni-no-se-va-milei-sostiene-al-vocero-pese-al-escandalo-y-las-advertencias-parte-del-gabinete-n5423597",
          "date": "2026-05-05T18:23:00+00:00",
          "category": "argentina"
        },
        {
          "title": "Los gastos de Manuel Adorni investigados por la Justicia superan los US$600.000 entre propiedades, refacciones y viajes",
          "source": "MDZ Online",
          "url": "https://www.mdzol.com/politica/los-gastos-manuel-adorni-investigados-la-justicia-superan-los-us600000-propiedades-refacciones-y-viajes-n1512703",
          "date": "2026-05-05T17:18:00+00:00",
          "category": "argentina"
        },
        {
          "title": "Javier Milei ratificó su apoyo a Manuel Adorni tras una declaración judicial que lo complica",
          "source": "La Gaceta",
          "url": "https://www.lagaceta.com.ar/nota/1135466/politica/javier-milei-ratifico-apoyo-manuel-adorni-tras-declaracion-judicial-lo-complica.html",
          "date": "2026-05-05T16:08:12+00:00",
          "category": "argentina"
        },
        {
          "title": "Causa Manuel Adorni: la Justicia investiga el origen de más de 350.000 de dólares pagados en efectivo",
          "source": "Diario Río Negro",
          "url": "https://www.rionegro.com.ar/justicia/causa-manuel-adorni-la-justicia-investiga-el-origen-de-mas-de-350-000-de-dolares-pagados-en-efectivo-4563084/",
          "date": "2026-05-05T14:23:12+00:00",
          "category": "argentina"
        },
        {
          "title": "Javier Milei paga carísimos los adornos multimillonarios de Manuel Adorni",
          "source": "Letra P",
          "url": "https://www.letrap.com.ar/javier-milei-paga-carisimos-los-adornos-multimillonarios-manuel-adorni-n5423585",
          "date": "2026-05-05T12:59:00+00:00",
          "category": "argentina"
        },
        {
          "title": "¿Cuántos dólares en efectivo gastó Manuel Adorni? Los números que están bajo la lupa de la justicia",
          "source": "Clarin.com",
          "url": "https://www.clarin.com/politica/dolares-efectivo-gasto-manuel-adorni-numeros-lupa-justicia_0_QRthjorQRr.html",
          "date": "2026-05-05T11:01:14+00:00",
          "category": "argentina"
        }
      ],
      "first_seen": "2026-05-05T03:56:52+00:00",
      "last_seen": "2026-05-06T04:12:42+00:00"
    },
    {
      "id": "trumps-iran-war-escalation-and-diplomacy",
      "title": "Trump’s Iran war escalation and diplomacy",
      "blurb": "President Trump’s administration faces backlash over its handling of the Iran conflict, including the pause of 'Project Freedom' in the Strait of Hormuz and accusations of erratic diplomacy. MAGA influencers and allies criticize the war’s economic and strategic impact.",
      "affect": "This story dominates due to its high-stakes geopolitical framing, polarized contention between Trump allies and critics, and alarmist rhetoric about war and economic consequences.",
      "intensity": 5,
      "affect_signals": [
        "polarized contention",
        "alarmist framing",
        "cross-source repetition",
        "outrage-coded language",
        "moral panic register"
      ],
      "categories": [
        "MAGA / Trump"
      ],
      "article_count": 100,
      "refs": [
        {
          "title": "World Insights: Top U.S. MAGA influencers turn against Trump over Iran war",
          "source": "Xinhua",
          "url": "https://english.news.cn/20260506/c177118ba1b74e2cb2dc684e9cdea82e/c.html",
          "date": "2026-05-06T02:37:15+00:00",
          "category": "usa"
        },
        {
          "title": "Data shows ICE is arresting 8x as many people under the Trump administration",
          "source": "KUSA.com",
          "url": "https://www.9news.com/article/news/local/next/next-with-kyle-clark/data-ice-trump-administration/73-c5481163-1a5b-4b99-969a-056be7ab0d2a",
          "date": "2026-05-06T01:41:00+00:00",
          "category": "usa"
        },
        {
          "title": "Trump says 'Project Freedom' to be paused 'for a short period of time'",
          "source": "BBC",
          "url": "https://www.bbc.com/news/articles/clypekl71gdo",
          "date": "2026-05-06T00:48:00+00:00",
          "category": "usa"
        },
        {
          "title": "Iran war: Trump says Project Freedom 'paused'",
          "source": "dw.com",
          "url": "https://www.dw.com/en/iran-war-trump-says-project-freedom-paused/live-77059422",
          "date": "2026-05-06T00:24:16+00:00",
          "category": "usa"
        },
        {
          "title": "President Trump to pause 'Project Freedom' in Strait of Hormuz",
          "source": "NBC News",
          "url": "https://www.nbcnews.com/video/president-trump-to-pause-project-freedom-in-strait-of-hormuz-262809669639",
          "date": "2026-05-05T23:29:02+00:00",
          "category": "usa"
        },
        {
          "title": "Defense Secretary Pete Hegseth says the U.S.- Iran ceasefire is holding",
          "source": "CBS News",
          "url": "https://www.cbsnews.com/boston/video/defense-secretary-pete-hegseth-says-the-u-s-iran-ceasefire-is-holding/",
          "date": "2026-05-05T21:16:00+00:00",
          "category": "usa"
        },
        {
          "title": "'Small price to pay' | President Trump on the economic impact of the war in Iran",
          "source": "kare11.com",
          "url": "https://www.kare11.com/video/news/nation-world/small-price-to-pay-president-trump-on-the-economic-impact-of-the-war-in-iran/89-90c7f5e5-3ce0-4d79-b474-90479b0bd741",
          "date": "2026-05-05T20:11:00+00:00",
          "category": "usa"
        },
        {
          "title": "Video: Trump says Iran should ‘wave the white flag’",
          "source": "Al Jazeera",
          "url": "https://www.aljazeera.com/video/newsfeed/2026/5/5/video-trump-says-iran-should-wave-the-white-flag",
          "date": "2026-05-05T19:07:30+00:00",
          "category": "usa"
        },
        {
          "title": "Iran Launches Second Strike on UAE, President Trump Gives No Clear Answer on Ceasefire Violation",
          "source": "The Media Line",
          "url": "https://themedialine.org/headlines/iran-launches-second-strike-on-uae-president-trump-gives-no-clear-answer-on-ceasefire-violation/",
          "date": "2026-05-05T19:04:40+00:00",
          "category": "usa"
        },
        {
          "title": "Donald Trump must defeat Iran’s terror regime - opinion",
          "source": "The Jerusalem Post",
          "url": "https://www.jpost.com/opinion/article-895223",
          "date": "2026-05-05T17:00:20+00:00",
          "category": "usa"
        },
        {
          "title": "Taboo broken: Social Democrats join far right to bring down Romania's prime minister",
          "source": "Courthouse News",
          "url": "https://www.courthousenews.com/taboo-broken-social-democrats-join-far-right-to-bring-down-romanias-prime-minister/",
          "date": "2026-05-05T15:25:47+00:00",
          "category": "general"
        },
        {
          "title": "President Trump Announces ‘Shabbat 250’ Initiative as Part of Jewish American Heritage Month",
          "source": "The Media Line",
          "url": "https://themedialine.org/headlines/president-trump-announces-shabbat-250-initiative-as-part-of-jewish-american-heritage-month/",
          "date": "2026-05-05T14:58:25+00:00",
          "category": "usa"
        },
        {
          "title": "Prediction: The Stock Market Is About to Do Something President Trump Will Hate",
          "source": "24/7 Wall St.",
          "url": "https://247wallst.com/investing/2026/05/05/prediction-the-stock-market-is-about-to-do-something-president-trump-will-hate/",
          "date": "2026-05-05T12:38:04+00:00",
          "category": "usa"
        },
        {
          "title": "Damning Intel Leak Reveals How Trump Is Failing in His Main War Mission",
          "source": "The Daily Beast",
          "url": "https://www.thedailybeast.com/president-donald-trumps-own-military-intel-says-hes-failing-to-damage-iranian-nuclear-program/",
          "date": "2026-05-05T10:13:00+00:00",
          "category": "usa"
        },
        {
          "title": "Trump torn on Iran war plan after attacks on US ships in Strait of Hormuz - WSJ",
          "source": "The Jerusalem Post",
          "url": "https://www.jpost.com/middle-east/iran-news/article-895163",
          "date": "2026-05-05T07:27:40+00:00",
          "category": "usa"
        }
      ],
      "first_seen": "2026-05-04T04:27:34+00:00",
      "last_seen": "2026-05-06T04:12:42+00:00"
    },
    {
      "id": "javier-mileis-governance-and-scandals",
      "title": "Javier Milei’s governance and scandals",
      "blurb": "Argentinian President Javier Milei’s administration is embroiled in multiple scandals, including the Adorni case, plummeting approval ratings, and economic struggles. His U.S. trips and public defenses of allies add to the controversy.",
      "affect": "This hotspot is charged due to the leadership crisis tone, moral outrage over corruption allegations, and the juxtaposition of Milei’s anti-establishment rhetoric with perceived hypocrisy.",
      "intensity": 4,
      "affect_signals": [
        "leadership crisis tone",
        "moral outrage framing",
        "cross-source repetition",
        "polarized contention",
        "alarmist framing"
      ],
      "categories": [
        "La Libertad Avanza"
      ],
      "article_count": 80,
      "refs": [
        {
          "title": "Javier Milei y Luis Caputo no se bancaron las críticas de Domigo Cavallo y salieron a cruzarlo",
          "source": "MinutoUno",
          "url": "https://www.minutouno.com/economia/javier-milei-y-luis-caputo-no-se-bancaron-las-criticas-domigo-cavallo-y-salieron-cruzarlo-n6274377",
          "date": "2026-05-06T02:47:00+00:00",
          "category": "argentina"
        },
        {
          "title": "Javier Milei asistió a 16 provincias por la caída de ingresos en abril",
          "source": "Diario Río Negro",
          "url": "https://www.rionegro.com.ar/politica/javier-milei-asistio-a-16-provincias-por-la-caida-de-ingresos-en-abril-4564133/",
          "date": "2026-05-06T02:06:55+00:00",
          "category": "argentina"
        },
        {
          "title": "Financial Times: \"Javier Milei, de Argentina, golpeado por escándalos y desaceleración económica\"",
          "source": "Urgente24",
          "url": "https://urgente24.com/dinero/financial-times-javier-milei-argentina-golpeado-escandalos-y-desaceleracion-economica-n624073",
          "date": "2026-05-06T01:44:28+00:00",
          "category": "argentina"
        },
        {
          "title": "The Economist advirtió que Javier Milei enfrenta un escenario crítico",
          "source": "BAE Negocios",
          "url": "https://www.baenegocios.com/politica/the-economist-advirtio-sobre-el-escenario-critico-que-enfrenta-javier-milei-640/",
          "date": "2026-05-05T22:16:43+00:00",
          "category": "argentina"
        },
        {
          "title": "Javier Milei ya no es profeta en su tierra: el Círculo Rojo quiere cambios",
          "source": "Letra P",
          "url": "https://www.letrap.com.ar/economia/javier-milei-ya-no-es-profeta-su-tierra-el-circulo-rojo-quiere-cambios-n5423599",
          "date": "2026-05-05T20:08:00+00:00",
          "category": "argentina"
        },
        {
          "title": "El Financial Times advierte sobre el desgaste de Javier Milei",
          "source": "MinutoUno",
          "url": "https://www.minutouno.com/el-financial-times-advierte-el-desgaste-javier-milei-n6274209",
          "date": "2026-05-05T18:20:00+00:00",
          "category": "argentina"
        },
        {
          "title": "El peligroso asedio de Javier Milei contra el periodismo profesional",
          "source": "Perfil",
          "url": "https://www.perfil.com/noticias/opinion/el-peligroso-asedio-de-javier-milei-contra-el-periodismo-profesional.phtml",
          "date": "2026-05-05T16:46:12+00:00",
          "category": "argentina"
        },
        {
          "title": "El Financial Times ve a Javier Milei \"golpeado\" por Adorni pero también por la economía",
          "source": "Urgente24",
          "url": "https://urgente24.com/actualidad/el-financial-times-ve-javier-milei-golpeado-adorni-pero-tambien-la-economia-n624016",
          "date": "2026-05-05T15:39:00+00:00",
          "category": "argentina"
        },
        {
          "title": "Por el RIGI, Javier Milei cancela el \"decreto Chevron\", que impulsó a Vaca Muerta",
          "source": "Clarin.com",
          "url": "https://www.clarin.com/economia/rigi-javier-milei-cancela-decreto-chevron-impulso-vaca-muerta_0_VyT5ucrvkd.html",
          "date": "2026-05-05T15:01:45+00:00",
          "category": "argentina"
        },
        {
          "title": "Javier Milei alcanzó su peor nivel de aprobación",
          "source": "Perfil",
          "url": "https://www.perfil.com/noticias/reperfilar/javier-milei-alcanzo-su-peor-nivel-de-aprobacion.phtml",
          "date": "2026-05-05T13:08:16+00:00",
          "category": "argentina"
        },
        {
          "title": "El ocaso de la autocracia financiera entre Donald Trump y Javier Milei",
          "source": "Ambito",
          "url": "https://www.ambito.com/opiniones/el-ocaso-la-autocracia-financiera-donald-trump-y-javier-milei-n6273960",
          "date": "2026-05-05T11:17:30+00:00",
          "category": "argentina"
        },
        {
          "title": "Según MRBT, cae la imagen de Javier Milei en Posadas: El 60% de los encuestados tiene una opinión negativa acerca del Presidente",
          "source": "Portal Misiones",
          "url": "https://portalmisiones.com/segun-mrbt-cae-la-imagen-de-javier-milei-en-posadas-el-60-de-los-encuestados-tiene-una-opinion-negativa-acerca-del-presidente/",
          "date": "2026-05-05T10:22:10+00:00",
          "category": "argentina"
        },
        {
          "title": "El presidente argentino Javier Milei, golpeado por los escándalos y la ralentización económica",
          "source": "Expansión",
          "url": "https://www.expansion.com/economia/financial-times/2026/05/05/69f9a578468aeb0d038b4592.html",
          "date": "2026-05-05T08:13:28+00:00",
          "category": "argentina"
        },
        {
          "title": "El Gobierno de Javier Milei designó a las autoridades del ENRGE, el nuevo organismo regulador del sector energ",
          "source": "Crónica",
          "url": "https://www.cronica.com.ar/politica/el-gobierno-designo-a-las-autoridades-del-enrge/",
          "date": "2026-05-05T07:55:00+00:00",
          "category": "argentina"
        },
        {
          "title": "Gazdaság: Magyar Péter: Orbán Viktor az utolsó héten még teljesen kifosztaná az államkasszát",
          "source": "| hvg.hu",
          "url": "https://hvg.hu/gazdasag/20260505_magyar-peter-orban-viktor-penzszoras-allamkassza",
          "date": "2026-05-05T06:51:05+00:00",
          "category": "hungary"
        }
      ],
      "first_seen": "2026-05-04T04:27:34+00:00",
      "last_seen": "2026-05-06T04:12:42+00:00"
    },
    {
      "id": "voxs-national-priority-and-regional-pacts",
      "title": "Vox’s ‘national priority’ and regional pacts",
      "blurb": "Vox’s push for a 'national priority' policy in Spain’s regional parliaments, including Andalusia, has sparked controversy over its implications for immigration, welfare, and housing. The party’s alliances with PP and internal strife add to the tension.",
      "affect": "This story is charged due to its polarized contention over immigration, moral panic over welfare access, and the high-stakes framing of regional elections as a referendum on national identity.",
      "intensity": 4,
      "affect_signals": [
        "polarized contention",
        "moral panic register",
        "cross-source repetition",
        "outrage-coded language",
        "leadership crisis tone"
      ],
      "categories": [
        "Vox"
      ],
      "article_count": 70,
      "refs": [
        {
          "title": "Vox recupera para el 17-M la ley de concordia que acordó promover con el PP en 2019 y nunca se aprobó",
          "source": "El Debate",
          "url": "https://www.eldebate.com/espana/andalucia/20260506/vox-recupera-17m-ley-concordia-acordo-promover-pp-2019-nunca-aprobo_414472.html",
          "date": "2026-05-06T02:30:00+00:00",
          "category": "spain"
        },
        {
          "title": "Prioridad electoral o el hombre invisible de Vox",
          "source": "Diario de Sevilla",
          "url": "https://www.diariodesevilla.es/opinion/analisis/prioridad-electoral-hombre-invisible-vox_0_2006684304.html",
          "date": "2026-05-06T01:07:25+00:00",
          "category": "spain"
        },
        {
          "title": "VP JD Vance joins Rep. Zach Nunn at campaign stop in Des Moines",
          "source": "KGAN",
          "url": "https://cbs2iowa.com/news/local/gallery/vp-jd-vance-to-join-rep-zach-nunn-at-campaign-stop-in-des-moines",
          "date": "2026-05-05T22:42:00+00:00",
          "category": "usa"
        },
        {
          "title": "Javier Cortés (Vox): “La prioridad nacional, al final, es la caridad con nuestra gente”",
          "source": "Andalucía Información",
          "url": "https://www.andaluciainformacion.es/articulo/elecciones-andalucia-17-mayo/javier-cortes-vox-prioridad-nacional-final-es-caridad-nuestra-gente/202605052331223254617.html",
          "date": "2026-05-05T21:31:22+00:00",
          "category": "spain"
        },
        {
          "title": "Gavira (Vox) llama a \"mandar al paro\" al PP y al PSOE el 17M",
          "source": "ABC",
          "url": "https://www.abc.es/espana/gavira-vox-llama-mandar-paro-pp-psoe-20260505224841-nt.html",
          "date": "2026-05-05T20:48:46+00:00",
          "category": "spain"
        },
        {
          "title": "Gavira llama a \"mandar al paro\" al PP y al PSOE el 17M",
          "source": "Andalucía Información",
          "url": "https://www.andaluciainformacion.es/articulo/elecciones-andalucia-17-mayo/gavira-vox-llama-mandar-paro-pp-psoe-17m/202605052203043254625.html",
          "date": "2026-05-05T20:03:04+00:00",
          "category": "spain"
        },
        {
          "title": "Pleno sobre el aborto: VOX se mantiene firme, mientras el PP suaviza su postura",
          "source": "Versión Radio",
          "url": "https://www.versionradio.es/pleno-sobre-el-aborto-vox-se-mantiene-firme-mientras-el-pp-suaviza-su-postura/",
          "date": "2026-05-05T17:53:17+00:00",
          "category": "spain"
        },
        {
          "title": "\"Prioridad nacional\", racismo, servicios públicos, vivienda... desmontamos el discurso de VOX en Aragón",
          "source": "Izquierda diario.es",
          "url": "https://www.izquierdadiario.es/Prioridad-nacional-racismo-servicios-publicos-vivienda-desmontamos-el-discurso-de-VOX-en-Aragon?amp=1",
          "date": "2026-05-05T17:26:29+00:00",
          "category": "spain"
        },
        {
          "title": "Vox registra una iniciativa que ajusta la \"prioridad nacional\" a lo pactado en Extremadura y Aragón y facilita el consenso con el PP",
          "source": "El Mundo",
          "url": "https://www.elmundo.es/espana/2026/05/05/69fa0232e85ece75698b4582.html",
          "date": "2026-05-05T15:53:49+00:00",
          "category": "spain"
        },
        {
          "title": "El PP rechaza debatir ya las reformas de la Ley de Mar Menor \"por mucho que Vox necesite tapar sus líos internos\"",
          "source": "La Opinión de Murcia",
          "url": "https://www.laopiniondemurcia.es/comunidad/2026/05/05/mar-menor-pp-vox-129876841.html",
          "date": "2026-05-05T14:59:52+00:00",
          "category": "spain"
        },
        {
          "title": "Este es el programa de Vox para las elecciones de Andalucía de 2026, con la 'prioridad nacional' por delante",
          "source": "LaSexta",
          "url": "https://www.lasexta.com/elecciones/autonomicas/este-programa-vox-elecciones-andalucia-2026-prioridad-nacional-delante_2026050569f9e5a12f817e65817b01bc.html",
          "date": "2026-05-05T12:50:52+00:00",
          "category": "spain"
        },
        {
          "title": "Vox incluye el arraigo en su propuesta sobre la 'prioridad nacional' en todos los Parlamentos",
          "source": "ABC",
          "url": "https://www.abc.es/sociedad/vox-incluye-arraigo-propuesta-sobre-prioridad-nacional-20260505140716-nt.html",
          "date": "2026-05-05T12:07:21+00:00",
          "category": "spain"
        },
        {
          "title": "Vox lleva prioridad nacional a todos los Parlamentos y exige arraigo \"verificable\" para ayudas",
          "source": "ABC",
          "url": "https://www.abc.es/espana/vox-lleva-prioridad-nacional-parlamentos-exige-arraigo-20260505120655-nt.html",
          "date": "2026-05-05T10:06:59+00:00",
          "category": "spain"
        },
        {
          "title": "Vox impulsa la prioridad nacional en todos los parlamentos y reclama arraigo verificable para acceder a ayudas públicas",
          "source": "Demócrata",
          "url": "https://www.democrata.es/politica/congreso-y-senado/vox-impulsa-la-prioridad-nacional-en-todos-los-parlamentos-y-reclama-arraigo-verificable-para-acceder-a-ayudas-publicas/",
          "date": "2026-05-05T09:37:19+00:00",
          "category": "spain"
        },
        {
          "title": "Vox crea la dirección general de desregulación y elimina inclusión social o educación ambiental",
          "source": "Aragón Digital",
          "url": "https://www.aragondigital.es/articulo/politica/vox-crea-direccion-general-desregulacion-elimina-inclusion-social-educacion-ambiental/20260505091500981631.html",
          "date": "2026-05-05T07:15:00+00:00",
          "category": "spain"
        }
      ],
      "first_seen": "2026-05-04T04:27:34+00:00",
      "last_seen": "2026-05-06T04:12:42+00:00"
    },
    {
      "id": "melonis-diplomatic-tensions-with-trump",
      "title": "Meloni’s diplomatic tensions with Trump",
      "blurb": "Italian Prime Minister Giorgia Meloni faces diplomatic strain with the Trump administration over NATO commitments, U.S. troop withdrawals, and Pope Leo XIV’s role in Iran diplomacy. Her handling of AI-generated deepfake attacks adds to the controversy.",
      "affect": "This hotspot is charged due to its geopolitical stakes, moral outrage over Trump’s criticisms, and the cross-source repetition of Meloni’s responses to deepfake attacks and NATO tensions.",
      "intensity": 4,
      "affect_signals": [
        "geopolitical stakes framing",
        "moral outrage framing",
        "cross-source repetition",
        "polarized contention",
        "leadership crisis tone"
      ],
      "categories": [
        "Fratelli d'Italia / Lega"
      ],
      "article_count": 60,
      "refs": [
        {
          "title": "Giorgia Meloni calls out sexualised deepfake, warns of growing threat to women in politics",
          "source": "Women's Agenda",
          "url": "https://womensagenda.com.au/latest/giorgia-meloni-calls-out-sexualised-deepfake-warns-of-growing-threat-to-women-in-politics/",
          "date": "2026-05-06T01:36:52+00:00",
          "category": "italy"
        },
        {
          "title": "Trump-Papa, le reazioni del governo. Meloni sceglie il silenzio, priorità all’asse con Rubio",
          "source": "Quotidiano Nazionale",
          "url": "https://www.quotidiano.net/politica/trump-papa-le-reazioni-del-governo-meloni-sceglie-il-silenzio-priorita-allasse-con-rubio-ocybo3k3",
          "date": "2026-05-05T23:31:56+00:00",
          "category": "italy"
        },
        {
          "title": "Giorgia Meloni criticises AI-generated photo of herself in lingerie",
          "source": "The Times",
          "url": "https://www.thetimes.com/world/europe/article/giorgia-meloni-ai-generated-photo-w7rd95gtj",
          "date": "2026-05-05T23:02:00+00:00",
          "category": "italy"
        },
        {
          "title": "Le torsioni di Meloni e l’ordine a FdI: “Noi alleati degli Usa e non di Donald”",
          "source": "La Stampa",
          "url": "https://www.lastampa.it/politica/2026/05/06/news/le_torsioni_di_meloni_e_l_ordine_a_fdi_noi_alleati_degli_usa_e_non_di_donald-15610793/",
          "date": "2026-05-05T23:00:00+00:00",
          "category": "italy"
        },
        {
          "title": "County leaders vote to rename Palm Beach airport after Donald Trump",
          "source": "WPLG Local 10",
          "url": "https://www.local10.com/news/local/2026/05/05/county-leaders-vote-to-rename-palm-beach-airport-after-donald-trump/",
          "date": "2026-05-05T22:17:09+00:00",
          "category": "usa"
        },
        {
          "title": "'Dangerous tool': Italian prime minister shares deepfake lingerie photo",
          "source": "9News",
          "url": "https://www.9news.com.au/world/italy-pm-giorgia-meloni-shares-deepfake-lingerie-post-to-denounce-dangerous-trend/891c140a-3564-43a4-a884-13d52d51d3b7",
          "date": "2026-05-05T20:39:39+00:00",
          "category": "italy"
        },
        {
          "title": "Meloni shares AI image of herself in lingerie to warn about deepfakes",
          "source": "The Telegraph",
          "url": "https://www.telegraph.co.uk/world-news/2026/05/05/meloni-shares-ai-image-of-herself-lingerie-deepfake-warning/",
          "date": "2026-05-05T20:31:00+00:00",
          "category": "italy"
        },
        {
          "title": "Italy PM Meloni warns over AI deepfakes after false photos of her circulate",
          "source": "South China Morning Post",
          "url": "https://www.scmp.com/news/world/europe/article/3352540/italy-pm-meloni-warns-over-ai-deepfakes-after-false-photos-her-circulate",
          "date": "2026-05-05T18:25:58+00:00",
          "category": "italy"
        },
        {
          "title": "‘Think before sharing,’ Giorgia Meloni says as AI-made lingerie image of her goes viral",
          "source": "The Guardian",
          "url": "https://www.theguardian.com/world/2026/may/05/giorgia-meloni-ai-generated-lingerie-image-deepfake",
          "date": "2026-05-05T17:11:00+00:00",
          "category": "italy"
        },
        {
          "title": "Italian PM Giorgia Meloni Warns of AI Deepfake Dangers",
          "source": "Devdiscourse",
          "url": "https://www.devdiscourse.com/article/technology/3897720-italian-pm-giorgia-meloni-warns-of-ai-deepfake-dangers",
          "date": "2026-05-05T15:34:44+00:00",
          "category": "italy"
        },
        {
          "title": "Meloni rilancia sua foto in lingerie generata con l’IA: “Deepfake pericolosi, colpiscono tutti”",
          "source": "la Repubblica",
          "url": "https://www.repubblica.it/politica/2026/05/05/news/deepfake_foto_meloni_lingerie_intelligenza_artificiale-425325299/",
          "date": "2026-05-05T14:52:45+00:00",
          "category": "italy"
        },
        {
          "title": "Meloni says stands with UAE, unjustifiable attacks must cease immediately (3)",
          "source": "ANSA",
          "url": "https://www.ansa.it/amp/english/newswire/english_service/2026/05/05/meloni-says-stands-with-uae-unjustifiable-attacks-must-cease-immediately_36f5e8b5-240a-4e8e-8056-0840657e7ddb.html",
          "date": "2026-05-05T13:01:08+00:00",
          "category": "italy"
        },
        {
          "title": "Meloni dall’Armenia risponde a Trump: “Noi con la Nato”",
          "source": "Tv2000",
          "url": "https://www.tv2000.it/tg2000/video/meloni-dallarmenia-risponde-a-trump-noi-con-la-nato/",
          "date": "2026-05-05T12:10:28+00:00",
          "category": "italy"
        },
        {
          "title": "Meloni vedrà Rubio ma affonda su Trump. \"Le critiche su di noi non sono corrette e non condivido il disimpegno Usa\"",
          "source": "il Giornale",
          "url": "https://www.ilgiornale.it/news/politica/meloni-vedr-rubio-affonda-su-trump-critiche-su-noi-non-sono-2659801.html",
          "date": "2026-05-05T10:02:29+00:00",
          "category": "italy"
        },
        {
          "title": "Truppe Usa, Meloni replica a Trump: “Non condivido, l’Italia ha sempre mantenuto gli impegni”",
          "source": "Affaritaliani",
          "url": "https://www.affaritaliani.it/esteri/truppe-usa-meloni-replica-a-trump-non-condivido-litalia-ha-sempre-mantenuto-gli-impegni.html",
          "date": "2026-05-05T08:32:52+00:00",
          "category": "italy"
        }
      ],
      "first_seen": "2026-05-05T03:56:52+00:00",
      "last_seen": "2026-05-06T04:12:42+00:00"
    }
  ]
}